dibas/__init__.py
dibas-0.1.0.dist-info/METADATA
dibas-0.1.0.dist-info/WHEEL
dibas-0.1.0.dist-info/top_level.txt
dibas-0.1.0.dist-info/RECORD
