Metadata-Version: 2.2
Name: dibas
Version: 0.1.0
Summary: A simple package that displays Dibas
Home-page: https://github.com/dibasdauliya/dibas-pip
Author: Dibas
Author-email: dibasdauliya@gmail.com
Classifier: Programming Language :: Python :: 3
Classifier: License :: OSI Approved :: MIT License
Classifier: Operating System :: OS Independent
Requires-Python: >=3.6
Dynamic: author
Dynamic: author-email
Dynamic: classifier
Dynamic: home-page
Dynamic: requires-python
Dynamic: summary
